argparge/__init__.py
argparge-0.1.5.dist-info/LICENSE
argparge-0.1.5.dist-info/METADATA
argparge-0.1.5.dist-info/WHEEL
argparge-0.1.5.dist-info/RECORD
